{
  "pageNumber": 121,
  "surahs": [
    {
      "surahNum": 5,
      "ayahs": [
        {
          "ayahNum": 77,
          "words": [
            {
              "text": "قُلْ",
              "code": "&#xfb51;",
              "indopak": "قُلۡ"
            },
            {
              "text": "يَـٰٓأَهْلَ",
              "code": "&#xfb52;",
              "indopak": "يٰۤـاَهۡلَ"
            },
            {
              "text": "ٱلْكِتَـٰبِ",
              "code": "&#xfb53;",
              "indopak": "الۡـكِتٰبِ"
            },
            {
              "text": "لَا",
              "code": "&#xfb54;",
              "indopak": "لَا"
            },
            {
              "text": "تَغْلُوا۟",
              "code": "&#xfb55;",
              "indopak": "تَغۡلُوۡا"
            },
            {
              "text": "فِى",
              "code": "&#xfb56;",
              "indopak": "فِىۡ"
            },
            {
              "text": "دِينِكُمْ",
              "code": "&#xfb57;",
              "indopak": "دِيۡـنِكُمۡ"
            },
            {
              "text": "غَيْرَ",
              "code": "&#xfb58;",
              "indopak": "غَيۡرَ"
            },
            {
              "text": "ٱلْحَقِّ",
              "code": "&#xfb59;",
              "isLastChar": true,
              "indopak": "الۡحَـقِّ"
            },
            {
              "text": "وَلَا",
              "code": "&#xfb5a;",
              "indopak": "وَلَا"
            },
            {
              "text": "تَتَّبِعُوٓا۟",
              "code": "&#xfb5b;",
              "indopak": "تَتَّبِعُوۡۤا"
            },
            {
              "text": "أَهْوَآءَ",
              "code": "&#xfb5c;",
              "indopak": "اَهۡوَآءَ"
            },
            {
              "text": "قَوْمٍ",
              "code": "&#xfb5d;",
              "indopak": "قَوۡمٍ"
            },
            {
              "text": "قَدْ",
              "code": "&#xfb5e;",
              "indopak": "قَدۡ"
            },
            {
              "text": "ضَلُّوا۟",
              "code": "&#xfb5f;",
              "indopak": "ضَلُّوۡا"
            },
            {
              "text": "مِن",
              "code": "&#xfb60;",
              "indopak": "مِنۡ"
            },
            {
              "text": "قَبْلُ",
              "code": "&#xfb61;",
              "indopak": "قَبۡلُ"
            },
            {
              "text": "وَأَضَلُّوا۟",
              "code": "&#xfb62;",
              "isLastChar": true,
              "indopak": "وَاَضَلُّوۡا"
            },
            {
              "text": "كَثِيرًا",
              "code": "&#xfb63;",
              "indopak": "كَثِيۡرًا"
            },
            {
              "text": "وَضَلُّوا۟",
              "code": "&#xfb64;",
              "indopak": "وَّضَلُّوۡا"
            },
            {
              "text": "عَن",
              "code": "&#xfb65;",
              "indopak": "عَنۡ"
            },
            {
              "text": "سَوَآءِ",
              "code": "&#xfb66;",
              "indopak": "سَوَآءِ"
            },
            {
              "text": "ٱلسَّبِيلِ",
              "code": "&#xfb67;",
              "indopak": "السَّبِيۡلِ"
            },
            {
              "text": null,
              "code": "&#xfb68;",
              "indopak": "٧٧"
            }
          ]
        },
        {
          "ayahNum": 78,
          "words": [
            {
              "text": "لُعِنَ",
              "code": "&#xfb69;",
              "indopak": "لُعِنَ"
            },
            {
              "text": "ٱلَّذِينَ",
              "code": "&#xfb6a;",
              "isLastChar": true,
              "indopak": "الَّذِيۡنَ"
            },
            {
              "text": "كَفَرُوا۟",
              "code": "&#xfb6b;",
              "indopak": "كَفَرُوۡا"
            },
            {
              "text": "مِنۢ",
              "code": "&#xfb6c;",
              "indopak": "مِنۡۢ"
            },
            {
              "text": "بَنِىٓ",
              "code": "&#xfb6d;",
              "indopak": "بَنِىۡۤ"
            },
            {
              "text": "إِسْرَٰٓءِيلَ",
              "code": "&#xfb6e;",
              "indopak": "اِسۡرَآءِيۡلَ"
            },
            {
              "text": "عَلَىٰ",
              "code": "&#xfb6f;",
              "indopak": "عَلٰى"
            },
            {
              "text": "لِسَانِ",
              "code": "&#xfb70;",
              "indopak": "لِسَانِ"
            },
            {
              "text": "دَاوُۥدَ",
              "code": "&#xfb71;",
              "indopak": "دَاوٗدَ"
            },
            {
              "text": "وَعِيسَى",
              "code": "&#xfb72;",
              "isLastChar": true,
              "indopak": "وَعِيۡسَى"
            },
            {
              "text": "ٱبْنِ",
              "code": "&#xfb73;",
              "indopak": "ابۡنِ"
            },
            {
              "text": "مَرْيَمَ",
              "code": "&#xfb74;",
              "indopak": "مَرۡيَمَ​ ؕ"
            },
            {
              "text": "ۚ",
              "code": "&#xfb75;",
              "indopak": ""
            },
            {
              "text": "ذَٰلِكَ",
              "code": "&#xfb76;",
              "indopak": "ذٰ لِكَ"
            },
            {
              "text": "بِمَا",
              "code": "&#xfb77;",
              "indopak": "بِمَا"
            },
            {
              "text": "عَصَوا۟",
              "code": "&#xfb78;",
              "indopak": "عَصَوْا"
            },
            {
              "text": "وَّكَانُوا۟",
              "code": "&#xfb79;",
              "indopak": "وَّكَانُوۡا"
            },
            {
              "text": "يَعْتَدُونَ",
              "code": "&#xfb7a;",
              "indopak": "يَعۡتَدُوۡنَ"
            },
            {
              "text": null,
              "code": "&#xfb7b;",
              "isLastChar": true,
              "indopak": "٧٨"
            }
          ]
        },
        {
          "ayahNum": 79,
          "words": [
            {
              "text": "كَانُوا۟",
              "code": "&#xfb7c;",
              "indopak": "كَانُوۡا"
            },
            {
              "text": "لَا",
              "code": "&#xfb7d;",
              "indopak": "لَا"
            },
            {
              "text": "يَتَنَاهَوْنَ",
              "code": "&#xfb7e;",
              "indopak": "يَتَـنَاهَوۡنَ"
            },
            {
              "text": "عَن",
              "code": "&#xfb7f;",
              "indopak": "عَنۡ"
            },
            {
              "text": "مُّنكَرٍ",
              "code": "&#xfb80;",
              "indopak": "مُّنۡكَرٍ"
            },
            {
              "text": "فَعَلُوهُ",
              "code": "&#xfb81;",
              "indopak": "فَعَلُوۡهُ ​ؕ"
            },
            {
              "text": "ۚ",
              "code": "&#xfb82;",
              "indopak": ""
            },
            {
              "text": "لَبِئْسَ",
              "code": "&#xfb83;",
              "isLastChar": true,
              "indopak": "لَبِئۡسَ"
            },
            {
              "text": "مَا",
              "code": "&#xfb84;",
              "indopak": "مَا"
            },
            {
              "text": "كَانُوا۟",
              "code": "&#xfb85;",
              "indopak": "كَانُوۡا"
            },
            {
              "text": "يَفْعَلُونَ",
              "code": "&#xfb86;",
              "indopak": "يَفۡعَلُوۡنَ"
            },
            {
              "text": null,
              "code": "&#xfb87;",
              "indopak": "٧٩"
            }
          ]
        },
        {
          "ayahNum": 80,
          "words": [
            {
              "text": "تَرَىٰ",
              "code": "&#xfb88;",
              "indopak": "تَرٰى"
            },
            {
              "text": "كَثِيرًا",
              "code": "&#xfb89;",
              "indopak": "كَثِيۡرًا"
            },
            {
              "text": "مِّنْهُمْ",
              "code": "&#xfb8a;",
              "isLastChar": true,
              "indopak": "مِّنۡهُمۡ"
            },
            {
              "text": "يَتَوَلَّوْنَ",
              "code": "&#xfb8b;",
              "indopak": "يَتَوَلَّوۡنَ"
            },
            {
              "text": "ٱلَّذِينَ",
              "code": "&#xfb8c;",
              "indopak": "الَّذِيۡنَ"
            },
            {
              "text": "كَفَرُوا۟",
              "code": "&#xfb8d;",
              "indopak": "كَفَرُوۡا​ؕ"
            },
            {
              "text": "ۚ",
              "code": "&#xfb8e;",
              "indopak": ""
            },
            {
              "text": "لَبِئْسَ",
              "code": "&#xfb8f;",
              "indopak": "لَبِئۡسَ"
            },
            {
              "text": "مَا",
              "code": "&#xfb90;",
              "indopak": "مَا"
            },
            {
              "text": "قَدَّمَتْ",
              "code": "&#xfb91;",
              "indopak": "قَدَّمَتۡ"
            },
            {
              "text": "لَهُمْ",
              "code": "&#xfb92;",
              "indopak": "لَهُمۡ"
            },
            {
              "text": "أَنفُسُهُمْ",
              "code": "&#xfb93;",
              "isLastChar": true,
              "indopak": "اَنۡفُسُهُمۡ"
            },
            {
              "text": "أَن",
              "code": "&#xfb94;",
              "indopak": "اَنۡ"
            },
            {
              "text": "سَخِطَ",
              "code": "&#xfb95;",
              "indopak": "سَخِطَ"
            },
            {
              "text": "ٱللَّهُ",
              "code": "&#xfb96;",
              "indopak": "اللّٰهُ"
            },
            {
              "text": "عَلَيْهِمْ",
              "code": "&#xfb97;",
              "indopak": "عَلَيۡهِمۡ"
            },
            {
              "text": "وَفِى",
              "code": "&#xfb98;",
              "indopak": "وَفِى"
            },
            {
              "text": "ٱلْعَذَابِ",
              "code": "&#xfb99;",
              "indopak": "الۡعَذَابِ"
            },
            {
              "text": "هُمْ",
              "code": "&#xfb9a;",
              "indopak": "هُمۡ"
            },
            {
              "text": "خَـٰلِدُونَ",
              "code": "&#xfb9b;",
              "indopak": "خٰلِدُوۡنَ"
            },
            {
              "text": null,
              "code": "&#xfb9c;",
              "isLastChar": true,
              "indopak": "٨٠"
            }
          ]
        },
        {
          "ayahNum": 81,
          "words": [
            {
              "text": "وَلَوْ",
              "code": "&#xfb9d;",
              "indopak": "وَلَوۡ"
            },
            {
              "text": "كَانُوا۟",
              "code": "&#xfb9e;",
              "indopak": "كَانُوۡا"
            },
            {
              "text": "يُؤْمِنُونَ",
              "code": "&#xfb9f;",
              "indopak": "يُؤۡمِنُوۡنَ"
            },
            {
              "text": "بِٱللَّهِ",
              "code": "&#xfba0;",
              "indopak": "بِاللّٰهِ"
            },
            {
              "text": "وَٱلنَّبِىِّ",
              "code": "&#xfba1;",
              "indopak": "وَالنَّبِىِّ"
            },
            {
              "text": "وَمَآ",
              "code": "&#xfba2;",
              "indopak": "وَمَاۤ"
            },
            {
              "text": "أُنزِلَ",
              "code": "&#xfba3;",
              "indopak": "اُنۡزِلَ"
            },
            {
              "text": "إِلَيْهِ",
              "code": "&#xfba4;",
              "isLastChar": true,
              "indopak": "اِلَيۡهِ"
            },
            {
              "text": "مَا",
              "code": "&#xfba5;",
              "indopak": "مَا"
            },
            {
              "text": "ٱتَّخَذُوهُمْ",
              "code": "&#xfba6;",
              "indopak": "اتَّخَذُوۡهُمۡ"
            },
            {
              "text": "أَوْلِيَآءَ",
              "code": "&#xfba7;",
              "indopak": "اَوۡلِيَآءَ"
            },
            {
              "text": "وَلَـٰكِنَّ",
              "code": "&#xfba8;",
              "indopak": "وَلٰـكِنَّ"
            },
            {
              "text": "كَثِيرًا",
              "code": "&#xfba9;",
              "indopak": "كَثِيۡرًا"
            },
            {
              "text": "مِّنْهُمْ",
              "code": "&#xfbaa;",
              "indopak": "مِّنۡهُمۡ"
            },
            {
              "text": "فَـٰسِقُونَ",
              "code": "&#xfbab;",
              "isLastChar": true,
              "indopak": "فٰسِقُوۡنَ"
            },
            {
              "text": null,
              "code": "&#xfbac;",
              "indopak": "٨١"
            }
          ]
        },
        {
          "ayahNum": 82,
          "words": [
            {
              "text": "۞",
              "code": "&#xfbad;",
              "indopak": "۞"
            },
            {
              "text": "لَتَجِدَنَّ",
              "code": "&#xfbae;",
              "indopak": "لَـتَجِدَنَّ"
            },
            {
              "text": "أَشَدَّ",
              "code": "&#xfbaf;",
              "indopak": "اَشَدَّ"
            },
            {
              "text": "ٱلنَّاسِ",
              "code": "&#xfbb0;",
              "indopak": "النَّاسِ"
            },
            {
              "text": "عَدَٰوَةً",
              "code": "&#xfbb1;",
              "indopak": "عَدَاوَةً"
            },
            {
              "text": "لِّلَّذِينَ",
              "code": "&#xfbd3;",
              "indopak": "لِّـلَّذِيۡنَ"
            },
            {
              "text": "ءَامَنُوا۟",
              "code": "&#xfbd4;",
              "indopak": "اٰمَنُوا"
            },
            {
              "text": "ٱلْيَهُودَ",
              "code": "&#xfbd5;",
              "isLastChar": true,
              "indopak": "الۡيَهُوۡدَ"
            },
            {
              "text": "وَٱلَّذِينَ",
              "code": "&#xfbd6;",
              "indopak": "وَالَّذِيۡنَ"
            },
            {
              "text": "أَشْرَكُوا۟",
              "code": "&#xfbd7;",
              "indopak": "اَشۡرَكُوۡا​ ۚ"
            },
            {
              "text": "ۖ",
              "code": "&#xfbd8;",
              "indopak": ""
            },
            {
              "text": "وَلَتَجِدَنَّ",
              "code": "&#xfbd9;",
              "indopak": "وَلَـتَجِدَنَّ"
            },
            {
              "text": "أَقْرَبَهُم",
              "code": "&#xfbda;",
              "indopak": "اَ قۡرَبَهُمۡ"
            },
            {
              "text": "مَّوَدَّةً",
              "code": "&#xfbdb;",
              "indopak": "مَّوَدَّةً"
            },
            {
              "text": "لِّلَّذِينَ",
              "code": "&#xfbdc;",
              "isLastChar": true,
              "indopak": "لِّـلَّذِيۡنَ"
            },
            {
              "text": "ءَامَنُوا۟",
              "code": "&#xfbdd;",
              "indopak": "اٰمَنُوا"
            },
            {
              "text": "ٱلَّذِينَ",
              "code": "&#xfbde;",
              "indopak": "الَّذِيۡنَ"
            },
            {
              "text": "قَالُوٓا۟",
              "code": "&#xfbdf;",
              "indopak": "قَالُوۡۤا"
            },
            {
              "text": "إِنَّا",
              "code": "&#xfbe0;",
              "indopak": "اِنَّا"
            },
            {
              "text": "نَصَـٰرَىٰ",
              "code": "&#xfbe1;",
              "indopak": "نَصٰرٰى​ ؕ"
            },
            {
              "text": "ۚ",
              "code": "&#xfbe2;",
              "indopak": ""
            },
            {
              "text": "ذَٰلِكَ",
              "code": "&#xfbe3;",
              "indopak": "ذٰ لِكَ"
            },
            {
              "text": "بِأَنَّ",
              "code": "&#xfbe4;",
              "indopak": "بِاَنَّ"
            },
            {
              "text": "مِنْهُمْ",
              "code": "&#xfbe5;",
              "isLastChar": true,
              "indopak": "مِنۡهُمۡ"
            },
            {
              "text": "قِسِّيسِينَ",
              "code": "&#xfbe6;",
              "indopak": "قِسِّيۡسِيۡنَ"
            },
            {
              "text": "وَرُهْبَانًا",
              "code": "&#xfbe7;",
              "indopak": "وَرُهۡبَانًا"
            },
            {
              "text": "وَأَنَّهُمْ",
              "code": "&#xfbe8;",
              "indopak": "وَّاَنَّهُمۡ"
            },
            {
              "text": "لَا",
              "code": "&#xfbe9;",
              "indopak": "لَا"
            },
            {
              "text": "يَسْتَكْبِرُونَ",
              "code": "&#xfbea;",
              "indopak": "يَسۡتَكۡبِرُوۡنَ"
            },
            {
              "text": null,
              "code": "&#xfbeb;",
              "indopak": "٨٢"
            }
          ]
        }
      ]
    }
  ],
  "juz": 6,
  "hizb": 48
}