{
  "pageNumber": 447,
  "surahs": [
    {
      "surahNum": 37,
      "ayahs": [
        {
          "ayahNum": 25,
          "words": [
            {
              "text": "مَا",
              "code": "&#xfb51;"
            },
            {
              "text": "لَكُمْ",
              "code": "&#xfb52;"
            },
            {
              "text": "لَا",
              "code": "&#xfb53;"
            },
            {
              "text": "تَنَاصَرُونَ",
              "code": "&#xfb54;"
            },
            {
              "text": null,
              "code": "&#xfb55;"
            }
          ]
        },
        {
          "ayahNum": 26,
          "words": [
            {
              "text": "بَلْ",
              "code": "&#xfb56;"
            },
            {
              "text": "هُمُ",
              "code": "&#xfb57;"
            },
            {
              "text": "ٱلْيَوْمَ",
              "code": "&#xfb58;"
            },
            {
              "text": "مُسْتَسْلِمُونَ",
              "code": "&#xfb59;"
            },
            {
              "text": null,
              "code": "&#xfb5a;"
            }
          ]
        },
        {
          "ayahNum": 27,
          "words": [
            {
              "text": "وَأَقْبَلَ",
              "code": "&#xfb5b;"
            },
            {
              "text": "بَعْضُهُمْ",
              "code": "&#xfb5c;",
              "isLastChar": true
            },
            {
              "text": "عَلَىٰ",
              "code": "&#xfb5d;"
            },
            {
              "text": "بَعْضٍ",
              "code": "&#xfb5e;"
            },
            {
              "text": "يَتَسَآءَلُونَ",
              "code": "&#xfb5f;"
            },
            {
              "text": null,
              "code": "&#xfb60;"
            }
          ]
        },
        {
          "ayahNum": 28,
          "words": [
            {
              "text": "قَالُوٓا۟",
              "code": "&#xfb61;"
            },
            {
              "text": "إِنَّكُمْ",
              "code": "&#xfb62;"
            },
            {
              "text": "كُنتُمْ",
              "code": "&#xfb63;"
            },
            {
              "text": "تَأْتُونَنَا",
              "code": "&#xfb64;"
            },
            {
              "text": "عَنِ",
              "code": "&#xfb65;"
            },
            {
              "text": "ٱلْيَمِينِ",
              "code": "&#xfb66;"
            },
            {
              "text": null,
              "code": "&#xfb67;",
              "isLastChar": true
            }
          ]
        },
        {
          "ayahNum": 29,
          "words": [
            {
              "text": "قَالُوا۟",
              "code": "&#xfb68;"
            },
            {
              "text": "بَل",
              "code": "&#xfb69;"
            },
            {
              "text": "لَّمْ",
              "code": "&#xfb6a;"
            },
            {
              "text": "تَكُونُوا۟",
              "code": "&#xfb6b;"
            },
            {
              "text": "مُؤْمِنِينَ",
              "code": "&#xfb6c;"
            },
            {
              "text": null,
              "code": "&#xfb6d;"
            }
          ]
        },
        {
          "ayahNum": 30,
          "words": [
            {
              "text": "وَمَا",
              "code": "&#xfb6e;"
            },
            {
              "text": "كَانَ",
              "code": "&#xfb6f;"
            },
            {
              "text": "لَنَا",
              "code": "&#xfb70;"
            },
            {
              "text": "عَلَيْكُم",
              "code": "&#xfb71;"
            },
            {
              "text": "مِّن",
              "code": "&#xfb72;"
            },
            {
              "text": "سُلْطَـٰنٍۭ",
              "code": "&#xfb73;"
            },
            {
              "text": "ۖ",
              "code": "&#xfb74;",
              "isLastChar": true
            },
            {
              "text": "بَلْ",
              "code": "&#xfb75;"
            },
            {
              "text": "كُنتُمْ",
              "code": "&#xfb76;"
            },
            {
              "text": "قَوْمًا",
              "code": "&#xfb77;"
            },
            {
              "text": "طَـٰغِينَ",
              "code": "&#xfb78;"
            },
            {
              "text": null,
              "code": "&#xfb79;"
            }
          ]
        },
        {
          "ayahNum": 31,
          "words": [
            {
              "text": "فَحَقَّ",
              "code": "&#xfb7a;"
            },
            {
              "text": "عَلَيْنَا",
              "code": "&#xfb7b;"
            },
            {
              "text": "قَوْلُ",
              "code": "&#xfb7c;"
            },
            {
              "text": "رَبِّنَآ",
              "code": "&#xfb7d;"
            },
            {
              "text": "ۖ",
              "code": "&#xfb7e;"
            },
            {
              "text": "إِنَّا",
              "code": "&#xfb7f;"
            },
            {
              "text": "لَذَآئِقُونَ",
              "code": "&#xfb80;"
            },
            {
              "text": null,
              "code": "&#xfb81;",
              "isLastChar": true
            }
          ]
        },
        {
          "ayahNum": 32,
          "words": [
            {
              "text": "فَأَغْوَيْنَـٰكُمْ",
              "code": "&#xfb82;"
            },
            {
              "text": "إِنَّا",
              "code": "&#xfb83;"
            },
            {
              "text": "كُنَّا",
              "code": "&#xfb84;"
            },
            {
              "text": "غَـٰوِينَ",
              "code": "&#xfb85;"
            },
            {
              "text": null,
              "code": "&#xfb86;"
            }
          ]
        },
        {
          "ayahNum": 33,
          "words": [
            {
              "text": "فَإِنَّهُمْ",
              "code": "&#xfb87;"
            },
            {
              "text": "يَوْمَئِذٍ",
              "code": "&#xfb88;"
            },
            {
              "text": "فِى",
              "code": "&#xfb89;"
            },
            {
              "text": "ٱلْعَذَابِ",
              "code": "&#xfb8a;"
            },
            {
              "text": "مُشْتَرِكُونَ",
              "code": "&#xfb8b;",
              "isLastChar": true
            },
            {
              "text": null,
              "code": "&#xfb8c;"
            }
          ]
        },
        {
          "ayahNum": 34,
          "words": [
            {
              "text": "إِنَّا",
              "code": "&#xfb8d;"
            },
            {
              "text": "كَذَٰلِكَ",
              "code": "&#xfb8e;"
            },
            {
              "text": "نَفْعَلُ",
              "code": "&#xfb8f;"
            },
            {
              "text": "بِٱلْمُجْرِمِينَ",
              "code": "&#xfb90;"
            },
            {
              "text": null,
              "code": "&#xfb91;"
            }
          ]
        },
        {
          "ayahNum": 35,
          "words": [
            {
              "text": "إِنَّهُمْ",
              "code": "&#xfb92;"
            },
            {
              "text": "كَانُوٓا۟",
              "code": "&#xfb93;"
            },
            {
              "text": "إِذَا",
              "code": "&#xfb94;"
            },
            {
              "text": "قِيلَ",
              "code": "&#xfb95;"
            },
            {
              "text": "لَهُمْ",
              "code": "&#xfb96;",
              "isLastChar": true
            },
            {
              "text": "لَآ",
              "code": "&#xfb97;"
            },
            {
              "text": "إِلَـٰهَ",
              "code": "&#xfb98;"
            },
            {
              "text": "إِلَّا",
              "code": "&#xfb99;"
            },
            {
              "text": "ٱللَّهُ",
              "code": "&#xfb9a;"
            },
            {
              "text": "يَسْتَكْبِرُونَ",
              "code": "&#xfb9b;"
            },
            {
              "text": null,
              "code": "&#xfb9c;"
            }
          ]
        },
        {
          "ayahNum": 36,
          "words": [
            {
              "text": "وَيَقُولُونَ",
              "code": "&#xfb9d;"
            },
            {
              "text": "أَئِنَّا",
              "code": "&#xfb9e;"
            },
            {
              "text": "لَتَارِكُوٓا۟",
              "code": "&#xfb9f;"
            },
            {
              "text": "ءَالِهَتِنَا",
              "code": "&#xfba0;",
              "isLastChar": true
            },
            {
              "text": "لِشَاعِرٍ",
              "code": "&#xfba1;"
            },
            {
              "text": "مَّجْنُونٍۭ",
              "code": "&#xfba2;"
            },
            {
              "text": null,
              "code": "&#xfba3;"
            }
          ]
        },
        {
          "ayahNum": 37,
          "words": [
            {
              "text": "بَلْ",
              "code": "&#xfba4;"
            },
            {
              "text": "جَآءَ",
              "code": "&#xfba5;"
            },
            {
              "text": "بِٱلْحَقِّ",
              "code": "&#xfba6;"
            },
            {
              "text": "وَصَدَّقَ",
              "code": "&#xfba7;"
            },
            {
              "text": "ٱلْمُرْسَلِينَ",
              "code": "&#xfba8;"
            },
            {
              "text": null,
              "code": "&#xfba9;"
            }
          ]
        },
        {
          "ayahNum": 38,
          "words": [
            {
              "text": "إِنَّكُمْ",
              "code": "&#xfbaa;",
              "isLastChar": true
            },
            {
              "text": "لَذَآئِقُوا۟",
              "code": "&#xfbab;"
            },
            {
              "text": "ٱلْعَذَابِ",
              "code": "&#xfbac;"
            },
            {
              "text": "ٱلْأَلِيمِ",
              "code": "&#xfbad;"
            },
            {
              "text": null,
              "code": "&#xfbae;"
            }
          ]
        },
        {
          "ayahNum": 39,
          "words": [
            {
              "text": "وَمَا",
              "code": "&#xfbaf;"
            },
            {
              "text": "تُجْزَوْنَ",
              "code": "&#xfbb0;"
            },
            {
              "text": "إِلَّا",
              "code": "&#xfbb1;"
            },
            {
              "text": "مَا",
              "code": "&#xfbd3;"
            },
            {
              "text": "كُنتُمْ",
              "code": "&#xfbd4;"
            },
            {
              "text": "تَعْمَلُونَ",
              "code": "&#xfbd5;",
              "isLastChar": true
            },
            {
              "text": null,
              "code": "&#xfbd6;"
            }
          ]
        },
        {
          "ayahNum": 40,
          "words": [
            {
              "text": "إِلَّا",
              "code": "&#xfbd7;"
            },
            {
              "text": "عِبَادَ",
              "code": "&#xfbd8;"
            },
            {
              "text": "ٱللَّهِ",
              "code": "&#xfbd9;"
            },
            {
              "text": "ٱلْمُخْلَصِينَ",
              "code": "&#xfbda;"
            },
            {
              "text": null,
              "code": "&#xfbdb;"
            }
          ]
        },
        {
          "ayahNum": 41,
          "words": [
            {
              "text": "أُو۟لَـٰٓئِكَ",
              "code": "&#xfbdc;"
            },
            {
              "text": "لَهُمْ",
              "code": "&#xfbdd;"
            },
            {
              "text": "رِزْقٌ",
              "code": "&#xfbde;"
            },
            {
              "text": "مَّعْلُومٌ",
              "code": "&#xfbdf;"
            },
            {
              "text": null,
              "code": "&#xfbe0;",
              "isLastChar": true
            }
          ]
        },
        {
          "ayahNum": 42,
          "words": [
            {
              "text": "فَوَٰكِهُ",
              "code": "&#xfbe1;"
            },
            {
              "text": "ۖ",
              "code": "&#xfbe2;"
            },
            {
              "text": "وَهُم",
              "code": "&#xfbe3;"
            },
            {
              "text": "مُّكْرَمُونَ",
              "code": "&#xfbe4;"
            },
            {
              "text": null,
              "code": "&#xfbe5;"
            }
          ]
        },
        {
          "ayahNum": 43,
          "words": [
            {
              "text": "فِى",
              "code": "&#xfbe6;"
            },
            {
              "text": "جَنَّـٰتِ",
              "code": "&#xfbe7;"
            },
            {
              "text": "ٱلنَّعِيمِ",
              "code": "&#xfbe8;"
            },
            {
              "text": null,
              "code": "&#xfbe9;"
            }
          ]
        },
        {
          "ayahNum": 44,
          "words": [
            {
              "text": "عَلَىٰ",
              "code": "&#xfbea;"
            },
            {
              "text": "سُرُرٍ",
              "code": "&#xfbeb;"
            },
            {
              "text": "مُّتَقَـٰبِلِينَ",
              "code": "&#xfbec;",
              "isLastChar": true
            },
            {
              "text": null,
              "code": "&#xfbed;"
            }
          ]
        },
        {
          "ayahNum": 45,
          "words": [
            {
              "text": "يُطَافُ",
              "code": "&#xfbee;"
            },
            {
              "text": "عَلَيْهِم",
              "code": "&#xfbef;"
            },
            {
              "text": "بِكَأْسٍ",
              "code": "&#xfbf0;"
            },
            {
              "text": "مِّن",
              "code": "&#xfbf1;"
            },
            {
              "text": "مَّعِينٍۭ",
              "code": "&#xfbf2;"
            },
            {
              "text": null,
              "code": "&#xfbf3;"
            }
          ]
        },
        {
          "ayahNum": 46,
          "words": [
            {
              "text": "بَيْضَآءَ",
              "code": "&#xfbf4;"
            },
            {
              "text": "لَذَّةٍ",
              "code": "&#xfbf5;"
            },
            {
              "text": "لِّلشَّـٰرِبِينَ",
              "code": "&#xfbf6;",
              "isLastChar": true
            },
            {
              "text": null,
              "code": "&#xfbf7;"
            }
          ]
        },
        {
          "ayahNum": 47,
          "words": [
            {
              "text": "لَا",
              "code": "&#xfbf8;"
            },
            {
              "text": "فِيهَا",
              "code": "&#xfbf9;"
            },
            {
              "text": "غَوْلٌ",
              "code": "&#xfbfa;"
            },
            {
              "text": "وَلَا",
              "code": "&#xfbfb;"
            },
            {
              "text": "هُمْ",
              "code": "&#xfbfc;"
            },
            {
              "text": "عَنْهَا",
              "code": "&#xfbfd;"
            },
            {
              "text": "يُنزَفُونَ",
              "code": "&#xfbfe;"
            },
            {
              "text": null,
              "code": "&#xfbff;"
            }
          ]
        },
        {
          "ayahNum": 48,
          "words": [
            {
              "text": "وَعِندَهُمْ",
              "code": "&#xfc00;"
            },
            {
              "text": "قَـٰصِرَٰتُ",
              "code": "&#xfc01;",
              "isLastChar": true
            },
            {
              "text": "ٱلطَّرْفِ",
              "code": "&#xfc02;"
            },
            {
              "text": "عِينٌ",
              "code": "&#xfc03;"
            },
            {
              "text": null,
              "code": "&#xfc04;"
            }
          ]
        },
        {
          "ayahNum": 49,
          "words": [
            {
              "text": "كَأَنَّهُنَّ",
              "code": "&#xfc05;"
            },
            {
              "text": "بَيْضٌ",
              "code": "&#xfc06;"
            },
            {
              "text": "مَّكْنُونٌ",
              "code": "&#xfc07;"
            },
            {
              "text": null,
              "code": "&#xfc08;"
            }
          ]
        },
        {
          "ayahNum": 50,
          "words": [
            {
              "text": "فَأَقْبَلَ",
              "code": "&#xfc09;"
            },
            {
              "text": "بَعْضُهُمْ",
              "code": "&#xfc0a;"
            },
            {
              "text": "عَلَىٰ",
              "code": "&#xfc0b;",
              "isLastChar": true
            },
            {
              "text": "بَعْضٍ",
              "code": "&#xfc0c;"
            },
            {
              "text": "يَتَسَآءَلُونَ",
              "code": "&#xfc0d;"
            },
            {
              "text": null,
              "code": "&#xfc0e;"
            }
          ]
        },
        {
          "ayahNum": 51,
          "words": [
            {
              "text": "قَالَ",
              "code": "&#xfc0f;"
            },
            {
              "text": "قَآئِلٌ",
              "code": "&#xfc10;"
            },
            {
              "text": "مِّنْهُمْ",
              "code": "&#xfc11;"
            },
            {
              "text": "إِنِّى",
              "code": "&#xfc12;"
            },
            {
              "text": "كَانَ",
              "code": "&#xfc13;"
            },
            {
              "text": "لِى",
              "code": "&#xfc14;"
            },
            {
              "text": "قَرِينٌ",
              "code": "&#xfc15;"
            },
            {
              "text": null,
              "code": "&#xfc16;"
            }
          ]
        }
      ]
    }
  ],
  "juz": 23,
  "hizb": 179
}