{
  "pageNumber": 511,
  "surahs": [
    {
      "surahNum": 48,
      "ayahs": [
        {
          "ayahNum": 1,
          "words": [
            {
              "text": "إِنَّا",
              "code": "&#xfb51;"
            },
            {
              "text": "فَتَحْنَا",
              "code": "&#xfb52;"
            },
            {
              "text": "لَكَ",
              "code": "&#xfb53;"
            },
            {
              "text": "فَتْحًا",
              "code": "&#xfb54;"
            },
            {
              "text": "مُبِينًا",
              "code": "&#xfb55;"
            },
            {
              "text": null,
              "code": "&#xfb56;"
            }
          ]
        },
        {
          "ayahNum": 2,
          "words": [
            {
              "text": "لِيَغْفِرَ",
              "code": "&#xfb57;"
            },
            {
              "text": "لَكَ",
              "code": "&#xfb58;"
            },
            {
              "text": "اللَّهُ",
              "code": "&#xfb59;"
            },
            {
              "text": "مَا",
              "code": "&#xfb5a;"
            },
            {
              "text": "تَقَدَّمَ",
              "code": "&#xfb5b;"
            },
            {
              "text": "مِنْ",
              "code": "&#xfb5c;"
            },
            {
              "text": "ذَنْبِكَ",
              "code": "&#xfb5d;",
              "isLastChar": true
            },
            {
              "text": "وَمَا",
              "code": "&#xfb5e;"
            },
            {
              "text": "تَأَخَّرَ",
              "code": "&#xfb5f;"
            },
            {
              "text": "وَيُتِمَّ",
              "code": "&#xfb60;"
            },
            {
              "text": "نِعْمَتَهُ",
              "code": "&#xfb61;"
            },
            {
              "text": "عَلَيْكَ",
              "code": "&#xfb62;"
            },
            {
              "text": "وَيَهْدِيَكَ",
              "code": "&#xfb63;"
            },
            {
              "text": "صِرَاطًا",
              "code": "&#xfb64;"
            },
            {
              "text": "مُسْتَقِيمًا",
              "code": "&#xfb65;"
            },
            {
              "text": null,
              "code": "&#xfb66;",
              "isLastChar": true
            }
          ]
        },
        {
          "ayahNum": 3,
          "words": [
            {
              "text": "وَيَنْصُرَكَ",
              "code": "&#xfb67;"
            },
            {
              "text": "اللَّهُ",
              "code": "&#xfb68;"
            },
            {
              "text": "نَصْرًا",
              "code": "&#xfb69;"
            },
            {
              "text": "عَزِيزًا",
              "code": "&#xfb6a;"
            },
            {
              "text": null,
              "code": "&#xfb6b;"
            }
          ]
        },
        {
          "ayahNum": 4,
          "words": [
            {
              "text": "هُوَ",
              "code": "&#xfb6c;"
            },
            {
              "text": "الَّذِي",
              "code": "&#xfb6d;"
            },
            {
              "text": "أَنْزَلَ",
              "code": "&#xfb6e;"
            },
            {
              "text": "السَّكِينَةَ",
              "code": "&#xfb6f;"
            },
            {
              "text": "فِي",
              "code": "&#xfb70;"
            },
            {
              "text": "قُلُوبِ",
              "code": "&#xfb71;",
              "isLastChar": true
            },
            {
              "text": "الْمُؤْمِنِينَ",
              "code": "&#xfb72;"
            },
            {
              "text": "لِيَزْدَادُوا",
              "code": "&#xfb73;"
            },
            {
              "text": "إِيمَانًا",
              "code": "&#xfb74;"
            },
            {
              "text": "مَعَ",
              "code": "&#xfb75;"
            },
            {
              "text": "إِيمَانِهِمْ",
              "code": "&#xfb76;"
            },
            {
              "text": "ۗ",
              "code": "&#xfb77;"
            },
            {
              "text": "وَلِلَّهِ",
              "code": "&#xfb78;"
            },
            {
              "text": "جُنُودُ",
              "code": "&#xfb79;"
            },
            {
              "text": "السَّمَاوَاتِ",
              "code": "&#xfb7a;",
              "isLastChar": true
            },
            {
              "text": "وَالْأَرْضِ",
              "code": "&#xfb7b;"
            },
            {
              "text": "ۚ",
              "code": "&#xfb7c;"
            },
            {
              "text": "وَكَانَ",
              "code": "&#xfb7d;"
            },
            {
              "text": "اللَّهُ",
              "code": "&#xfb7e;"
            },
            {
              "text": "عَلِيمًا",
              "code": "&#xfb7f;"
            },
            {
              "text": "حَكِيمًا",
              "code": "&#xfb80;"
            },
            {
              "text": null,
              "code": "&#xfb81;"
            }
          ]
        },
        {
          "ayahNum": 5,
          "words": [
            {
              "text": "لِيُدْخِلَ",
              "code": "&#xfb82;"
            },
            {
              "text": "الْمُؤْمِنِينَ",
              "code": "&#xfb83;"
            },
            {
              "text": "وَالْمُؤْمِنَاتِ",
              "code": "&#xfb84;",
              "isLastChar": true
            },
            {
              "text": "جَنَّاتٍ",
              "code": "&#xfb85;"
            },
            {
              "text": "تَجْرِي",
              "code": "&#xfb86;"
            },
            {
              "text": "مِنْ",
              "code": "&#xfb87;"
            },
            {
              "text": "تَحْتِهَا",
              "code": "&#xfb88;"
            },
            {
              "text": "الْأَنْهَارُ",
              "code": "&#xfb89;"
            },
            {
              "text": "خَالِدِينَ",
              "code": "&#xfb8a;"
            },
            {
              "text": "فِيهَا",
              "code": "&#xfb8b;"
            },
            {
              "text": "وَيُكَفِّرَ",
              "code": "&#xfb8c;"
            },
            {
              "text": "عَنْهُمْ",
              "code": "&#xfb8d;",
              "isLastChar": true
            },
            {
              "text": "سَيِّئَاتِهِمْ",
              "code": "&#xfb8e;"
            },
            {
              "text": "ۚ",
              "code": "&#xfb8f;"
            },
            {
              "text": "وَكَانَ",
              "code": "&#xfb90;"
            },
            {
              "text": "ذَٰلِكَ",
              "code": "&#xfb91;"
            },
            {
              "text": "عِنْدَ",
              "code": "&#xfb92;"
            },
            {
              "text": "اللَّهِ",
              "code": "&#xfb93;"
            },
            {
              "text": "فَوْزًا",
              "code": "&#xfb94;"
            },
            {
              "text": "عَظِيمًا",
              "code": "&#xfb95;"
            },
            {
              "text": null,
              "code": "&#xfb96;"
            }
          ]
        },
        {
          "ayahNum": 6,
          "words": [
            {
              "text": "وَيُعَذِّبَ",
              "code": "&#xfb97;",
              "isLastChar": true
            },
            {
              "text": "الْمُنَافِقِينَ",
              "code": "&#xfb98;"
            },
            {
              "text": "وَالْمُنَافِقَاتِ",
              "code": "&#xfb99;"
            },
            {
              "text": "وَالْمُشْرِكِينَ",
              "code": "&#xfb9a;"
            },
            {
              "text": "وَالْمُشْرِكَاتِ",
              "code": "&#xfb9b;"
            },
            {
              "text": "الظَّانِّينَ",
              "code": "&#xfb9c;",
              "isLastChar": true
            },
            {
              "text": "بِاللَّهِ",
              "code": "&#xfb9d;"
            },
            {
              "text": "ظَنَّ",
              "code": "&#xfb9e;"
            },
            {
              "text": "السَّوْءِ",
              "code": "&#xfb9f;"
            },
            {
              "text": "ۚ",
              "code": "&#xfba0;"
            },
            {
              "text": "عَلَيْهِمْ",
              "code": "&#xfba1;"
            },
            {
              "text": "دَائِرَةُ",
              "code": "&#xfba2;"
            },
            {
              "text": "السَّوْءِ",
              "code": "&#xfba3;"
            },
            {
              "text": "ۖ",
              "code": "&#xfba4;"
            },
            {
              "text": "وَغَضِبَ",
              "code": "&#xfba5;"
            },
            {
              "text": "اللَّهُ",
              "code": "&#xfba6;"
            },
            {
              "text": "عَلَيْهِمْ",
              "code": "&#xfba7;",
              "isLastChar": true
            },
            {
              "text": "وَلَعَنَهُمْ",
              "code": "&#xfba8;"
            },
            {
              "text": "وَأَعَدَّ",
              "code": "&#xfba9;"
            },
            {
              "text": "لَهُمْ",
              "code": "&#xfbaa;"
            },
            {
              "text": "جَهَنَّمَ",
              "code": "&#xfbab;"
            },
            {
              "text": "ۖ",
              "code": "&#xfbac;"
            },
            {
              "text": "وَسَاءَتْ",
              "code": "&#xfbad;"
            },
            {
              "text": "مَصِيرًا",
              "code": "&#xfbae;"
            },
            {
              "text": null,
              "code": "&#xfbaf;"
            }
          ]
        },
        {
          "ayahNum": 7,
          "words": [
            {
              "text": "وَلِلَّهِ",
              "code": "&#xfbb0;"
            },
            {
              "text": "جُنُودُ",
              "code": "&#xfbb1;",
              "isLastChar": true
            },
            {
              "text": "السَّمَاوَاتِ",
              "code": "&#xfbd3;"
            },
            {
              "text": "وَالْأَرْضِ",
              "code": "&#xfbd4;"
            },
            {
              "text": "ۚ",
              "code": "&#xfbd5;"
            },
            {
              "text": "وَكَانَ",
              "code": "&#xfbd6;"
            },
            {
              "text": "اللَّهُ",
              "code": "&#xfbd7;"
            },
            {
              "text": "عَزِيزًا",
              "code": "&#xfbd8;"
            },
            {
              "text": "حَكِيمًا",
              "code": "&#xfbd9;"
            },
            {
              "text": null,
              "code": "&#xfbda;"
            }
          ]
        },
        {
          "ayahNum": 8,
          "words": [
            {
              "text": "إِنَّا",
              "code": "&#xfbdb;"
            },
            {
              "text": "أَرْسَلْنَاكَ",
              "code": "&#xfbdc;",
              "isLastChar": true
            },
            {
              "text": "شَاهِدًا",
              "code": "&#xfbdd;"
            },
            {
              "text": "وَمُبَشِّرًا",
              "code": "&#xfbde;"
            },
            {
              "text": "وَنَذِيرًا",
              "code": "&#xfbdf;"
            },
            {
              "text": null,
              "code": "&#xfbe0;"
            }
          ]
        },
        {
          "ayahNum": 9,
          "words": [
            {
              "text": "لِتُؤْمِنُوا",
              "code": "&#xfbe1;"
            },
            {
              "text": "بِاللَّهِ",
              "code": "&#xfbe2;"
            },
            {
              "text": "وَرَسُولِهِ",
              "code": "&#xfbe3;",
              "isLastChar": true
            },
            {
              "text": "وَتُعَزِّرُوهُ",
              "code": "&#xfbe4;"
            },
            {
              "text": "وَتُوَقِّرُوهُ",
              "code": "&#xfbe5;"
            },
            {
              "text": "وَتُسَبِّحُوهُ",
              "code": "&#xfbe6;"
            },
            {
              "text": "بُكْرَةً",
              "code": "&#xfbe7;"
            },
            {
              "text": "وَأَصِيلًا",
              "code": "&#xfbe8;"
            },
            {
              "text": null,
              "code": "&#xfbe9;"
            }
          ]
        }
      ]
    }
  ],
  "juz": 26,
  "hizb": 204
}